gl_observability.cpython-312-darwin.so
gl_observability.pyi
gl_observability/__init__.pyi
gl_observability/initializer.pyi
gl_observability/backend/__init__.pyi
gl_observability/backend/opentelemetry/__init__.pyi
gl_observability/backend/opentelemetry/initializer.pyi
gl_observability/backend/sentry/__init__.pyi
gl_observability/backend/sentry/initializer.pyi
gl_observability/logs/__init__.pyi
gl_observability/logs/ner_pii_logger_handler.pyi
gl_observability/logs/regex_pii_logger_handler.pyi
gl_observability/traces/__init__.pyi
gl_observability/traces/opentelemetry/__init__.pyi
gl_observability/traces/opentelemetry/instrument/__init__.pyi
gl_observability/traces/opentelemetry/instrument/functions.pyi
gl_observability/traces/opentelemetry/instrument/http.pyi
gl_observability.build/.gitignore
gl_observability_binary-0.0.0b1.dist-info/METADATA
gl_observability_binary-0.0.0b1.dist-info/WHEEL
gl_observability_binary-0.0.0b1.dist-info/top_level.txt
gl_observability_binary-0.0.0b1.dist-info/RECORD
