Metadata-Version: 2.2
Name: gl-observability-binary
Version: 0.0.0b1
Summary: SDK for Observability tools
Author-email: HansSeanNathanael <hans.s.nathanael@gdplabs.id>
Requires-Python: <3.14,>=3.11
Requires-Dist: fastapi<1.0.0,>=0.115.6
Requires-Dist: requests<3.0.0,>=2.31.0
Requires-Dist: httpx<1.0.0,>=0.27.0
Requires-Dist: langchain-core<1.0.0,>=0.3
Requires-Dist: sentry-sdk<3.0.0,>=2.20.0
Requires-Dist: opentelemetry-api
Requires-Dist: opentelemetry-sdk
Requires-Dist: opentelemetry-exporter-otlp-proto-http
Requires-Dist: opentelemetry-exporter-otlp-proto-grpc
Requires-Dist: opentelemetry-instrumentation-fastapi
Requires-Dist: opentelemetry-instrumentation-langchain
Requires-Dist: opentelemetry-instrumentation-requests
Requires-Dist: opentelemetry-instrumentation-httpx
Provides-Extra: dev
Requires-Dist: pytest<9.0.0,>=8.3.4; extra == "dev"
Requires-Dist: pre-commit<4.0.0,>=3.7.0; extra == "dev"
Requires-Dist: pytest-cov<6.0.0,>=5.0.0; extra == "dev"
Requires-Dist: pytest-asyncio<1.0.0,>=0.25.3; extra == "dev"
Requires-Dist: pytest-mock<4.0.0,>=3.14.0; extra == "dev"
Requires-Dist: coverage<8.0.0,>=7.6.10; extra == "dev"
Requires-Dist: mypy<2.0.0,>=1.11.2; extra == "dev"
Requires-Dist: ruff<1.0.0,>=0.11.12; extra == "dev"
